MANIFEST.in
README.md
description.md
setup.cfg
setup.py
doc/HypoInvPy_manual.docx
example/.DS_Store
example/run_HypoInvPy_with_EQT_output.ipynb
example/run_HypoInvPy_with_GAMMA_output.ipynb
example/.ipynb_checkpoints/HypoInvPy_run_example-checkpoint.ipynb
example/__pycache__/config.cpython-311.pyc
example/input/.DS_Store
example/input/EQT_Y2000.phs
example/input/EQT_station_list.csv
example/input/EQT_station_list.json
example/input/EQT_station_list.sta
example/input/GAMMA_catalog.csv
example/input/GAMMA_picks.csv
example/input/GAMMA_station_list.json
example/input/velo_p_eg.cre
example/input/velo_s_eg.cre
example/input/.ipynb_checkpoints/HypoInvPy_dev_tests-checkpoint.ipynb
example/output/.DS_Store
example/output/hyp_bad.csv
example/output/hyp_good.csv
figs/hypoinvpylogo.pdf
figs/hypoinvpylogo.png
hyp1.40/hyp1.40-release-notes.pdf
hyp1.40/hyp1.40-release-notes.txt
hyp1.40/doc/hyp1.40.doc
hyp1.40/doc/hyp1.40.pdf
hyp1.40/source/.DS_Store
hyp1.40/source/allsubs.f
hyp1.40/source/box2.inc
hyp1.40/source/box3.inc
hyp1.40/source/common.inc
hyp1.40/source/hyate.for
hyp1.40/source/hybda.for
hyp1.40/source/hybeg.f
hyp1.40/source/hycal.for
hyp1.40/source/hycmd.for
hyp1.40/source/hycre.for
hyp1.40/source/hycrh.for
hyp1.40/source/hycrt.for
hyp1.40/source/hydatum.for
hyp1.40/source/hydel.for
hyp1.40/source/hydelt.f
hyp1.40/source/hyedit.f
hyp1.40/source/hyfile.for
hyp1.40/source/hyfmc.for
hyp1.40/source/hyinit.for
hyp1.40/source/hyinp.for
hyp1.40/source/hylin.for
hyp1.40/source/hylinv.for
hyp1.40/source/hyloc.for
hyp1.40/source/hylst.for
hyp1.40/source/hymag.for
hyp1.40/source/hymagp.for
hyp1.40/source/hyopen.for
hyp1.40/source/hyp.for
hyp1.40/source/hyphs.for
hyp1.40/source/hypref.for
hyp1.40/source/hypro.for
hyp1.40/source/hyrep.for
hyp1.40/source/hysol.for
hyp1.40/source/hysou.for
hyp1.40/source/hysta.for
hyp1.40/source/hystl.for
hyp1.40/source/hysum.for
hyp1.40/source/hysvd.f
hyp1.40/source/hytime.f
hyp1.40/source/hytra.for
hyp1.40/source/hytre.for
hyp1.40/source/hytrh.for
hypoinvpy.egg-info/PKG-INFO
hypoinvpy.egg-info/SOURCES.txt
hypoinvpy.egg-info/dependency_links.txt
hypoinvpy.egg-info/requires.txt
hypoinvpy.egg-info/top_level.txt
