Metadata-Version: 2.1
Name: hypoinvpy
Version: 0.7.0
Summary: A Python interface for HypoInverse earthquake relocation software
Home-page: https://github.com/xtyangpsp/HypoInvPy
Download-URL: https://github.com/xtyangpsp/HypoInvPy/archive/refs/tags/v0.7.0.tar.gz
Author: Xiaotao Yang
Author-email: stcyang@gmail.com
Maintainer: Xiaotao Yang
Maintainer-email: stcyang@gmail.com
License: MIT license
Keywords: seismology,earthquake relocation,hypoinverse
Classifier: Development Status :: 4 - Beta
Classifier: License :: OSI Approved :: MIT License
Classifier: Programming Language :: Python :: 3.10
Requires-Python: >=3.7
Requires-Dist: numpy
Requires-Dist: scipy
Requires-Dist: pandas
Requires-Dist: obspy
Requires-Dist: cartopy
Requires-Dist: tqdm
